pyfmm/__init__.py
pyfmm/_version.py
pyfmm/c_interfaces.py
pyfmm/logger.py
pyfmm/traveltime.py
pyfmm/C_extension/Makefile
pyfmm/C_extension/include/const.h
pyfmm/C_extension/include/coord.h
pyfmm/C_extension/include/diff.h
pyfmm/C_extension/include/fmm.h
pyfmm/C_extension/include/fsm.h
pyfmm/C_extension/include/heapsort.h
pyfmm/C_extension/include/index.h
pyfmm/C_extension/include/interp.h
pyfmm/C_extension/include/mallocfree.h
pyfmm/C_extension/include/progressbar.h
pyfmm/C_extension/include/query.h
pyfmm/C_extension/lib/libfmm_double.a
pyfmm/C_extension/lib/libfmm_double.so
pyfmm/C_extension/lib/libfmm_float.a
pyfmm/C_extension/lib/libfmm_float.so
pyfmm/C_extension/src/diff.c
pyfmm/C_extension/src/fmm.c
pyfmm/C_extension/src/fsm.c
pyfmm/C_extension/src/heapsort.c
pyfmm/C_extension/src/interp.c
pyfmm/C_extension/src/mallocfree.c
pyfmm/C_extension/src/progressbar.c
pyfmm/C_extension/src/query.c
pyfmm_kit-0.5.0.dist-info/licenses/LICENSE
pyfmm_kit-0.5.0.dist-info/METADATA
pyfmm_kit-0.5.0.dist-info/WHEEL
pyfmm_kit-0.5.0.dist-info/top_level.txt
pyfmm_kit-0.5.0.dist-info/RECORD
