Metadata-Version: 2.4
Name: pyfmm-kit
Version: 0.5.0
Summary: A C/Python package for solving eikonal equation using Fast Marching/Sweeping Method
Home-page: https://github.com/Dengda98/PyFMM
Author: Zhu Dengda
Author-email: zhudengda@mail.iggcas.ac.cn
Project-URL: Documentation, https://pyfmm.readthedocs.io/zh-cn/latest/
Project-URL: Source Code, https://github.com/Dengda98/PyFMM
Requires-Python: >=3.6
License-File: LICENSE
Requires-Dist: numpy<2.0,>=1.20
Requires-Dist: scipy>=1.10
Requires-Dist: matplotlib>=3.5
Requires-Dist: jupyter
Dynamic: author
Dynamic: author-email
Dynamic: description
Dynamic: description-content-type
Dynamic: home-page
Dynamic: license-file
Dynamic: project-url
Dynamic: requires-dist
Dynamic: requires-python
Dynamic: summary
